{
  "charter": {
    "nome": "Projetos Dinâmicos",
    "descricao": "Gerenciador visual de projetos e atividades com mapa interativo, dashboard de progresso e sistema de feedbacks",
    "patrocinador": "Wander",
    "gerente_projeto": "Wander",
    "data_inicio": "2024-03-08",
    "data_fim_estimada": "2026-12-31",
    "orcamento_estimado": "500 horas",
    "stakeholders": [
      {"nome": "Wander", "papel": "Patrocinador/Desenvolvedor", "interesse": "Alto"},
      {"nome": "Usuários finais", "papel": "Stakeholder", "interesse": "Médio"}
    ],
    "objetivos": [
      "Criar interface visual para gestão de projetos",
      "Implementar mapa interativo de atividades",
      "Desenvolver dashboard de progresso",
      "Adicionar sistema de feedbacks",
      "Disponibilizar versão mobile via Capacitor",
      "Disponibilizar versão desktop via Tauri"
    ],
    "restricoes": [
      "Tecnologia web (HTML/CSS/JS)",
      "Sem backend (dados locais)",
      "Compatibilidade com navegadores modernos"
    ],
    "riscos_iniciais": [
      {"descricao": "Escopo pode expandir além do necessário", "probabilidade": "Alta", "impacto": "Médio"},
      {"descricao": "Dados localStorage podem ser perdidos", "probabilidade": "Média", "impacto": "Alto"},
      {"descricao": "Dificuldade em exportar dados", "probabilidade": "Média", "impacto": "Baixo"}
    ]
  },
  "eap": {
    "fase_1_iniciacao": {
      "nome": "Iniciação",
      "pacotes": [
        {"id": "EAP-1.1", "nome": "Definir requisitos", "responsavel": "Wander", "horas_estimadas": 8, "status": "concluido"},
        {"id": "EAP-1.2", "nome": "Criar documento de visão", "responsavel": "Wander", "horas_estimadas": 4, "status": "concluido"},
        {"id": "EAP-1.3", "nome": "Definir arquitetura técnica", "responsavel": "Wander", "horas_estimadas": 8, "status": "concluido"}
      ]
    },
    "fase_2_planejamento": {
      "nome": "Planejamento",
      "pacotes": [
        {"id": "EAP-2.1", "nome": "Criar estrutura de diretórios", "responsavel": "Wander", "horas_estimadas": 2, "status": "concluido"},
        {"id": "EAP-2.2", "nome": "Definir templates de projetos", "responsavel": "Wander", "horas_estimadas": 8, "status": "concluido"},
        {"id": "EAP-2.3", "nome": "Planejar sistema de dados", "responsavel": "Wander", "horas_estimadas": 4, "status": "em_andamento"}
      ]
    },
    "fase_3_execucao": {
      "nome": "Execução - Frontend",
      "pacotes": [
        {"id": "EAP-3.1", "nome": "Criar estrutura HTML base", "responsavel": "Wander", "horas_estimadas": 16, "status": "concluido"},
        {"id": "EAP-3.2", "nome": "Implementar CSS global", "responsavel": "Wander", "horas_estimadas": 12, "status": "concluido"},
        {"id": "EAP-3.3", "nome": "Desenvolver componente Header", "responsavel": "Wander", "horas_estimadas": 4, "status": "concluido"},
        {"id": "EAP-3.4", "nome": "Desenvolver componente Footer", "responsavel": "Wander", "horas_estimadas": 2, "status": "concluido"},
        {"id": "EAP-3.5", "nome": "Implementar dashboard de projetos", "responsavel": "Wander", "horas_estimadas": 16, "status": "em_andamento"},
        {"id": "EAP-3.6", "nome": "Criar sistema de modais", "responsavel": "Wander", "horas_estimadas": 8, "status": "em_andamento"}
      ]
    },
    "fase_4_executar_mapa": {
      "nome": "Execução - Mapa Visual",
      "pacotes": [
        {"id": "EAP-4.1", "nome": "Implementar engine do mapa", "responsavel": "Wander", "horas_estimadas": 20, "status": "em_andamento"},
        {"id": "EAP-4.2", "nome": "Adicionar sistema de drag-and-drop", "responsavel": "Wander", "horas_estimadas": 8, "status": "pendente"},
        {"id": "EAP-4.3", "nome": "Criar painel de dependências", "responsavel": "Wander", "horas_estimadas": 8, "status": "pendente"}
      ]
    },
    "fase_5_executar_kanban": {
      "nome": "Execução - Kanban",
      "pacotes": [
        {"id": "EAP-5.1", "nome": "Implementar board kanban", "responsavel": "Wander", "horas_estimadas": 16, "status": "em_andamento"},
        {"id": "EAP-5.2", "nome": "Adicionar drag entre colunas", "responsavel": "Wander", "horas_estimadas": 8, "status": "pendente"}
      ]
    },
    "fase_6_mobile": {
      "nome": "Execução - Mobile",
      "pacotes": [
        {"id": "EAP-6.1", "nome": "Configurar Capacitor", "responsavel": "Wander", "horas_estimadas": 4, "status": "concluido"},
        {"id": "EAP-6.2", "nome": "Configurar Tauri", "responsavel": "Wander", "horas_estimadas": 4, "status": "concluido"},
        {"id": "EAP-6.3", "nome": "Compilar versão Android", "responsavel": "Wander", "horas_estimadas": 8, "status": "pendente"}
      ]
    },
    "fase_7_encerramento": {
      "nome": "Encerramento",
      "pacotes": [
        {"id": "EAP-7.1", "nome": "Documentar lições aprendidas", "responsavel": "Wander", "horas_estimadas": 4, "status": "pendente"},
        {"id": "EAP-7.2", "nome": "Criar guia de usuário", "responsavel": "Wander", "horas_estimadas": 8, "status": "pendente"},
        {"id": "EAP-7.3", "nome": "Arquivar documentação", "responsavel": "Wander", "horas_estimadas": 2, "status": "pendente"}
      ]
    }
  },
  "raci": {
    "papéis": ["Patrocinador", "Gerente Projeto", "Desenvolvedor", "Revisor"],
    "atividades": [
      {"atividade": "Definir requisitos", "R": "Gerente Projeto", "A": "Patrocinador", "C": "", "I": ""},
      {"atividade": "Criar arquitetura", "R": "Gerente Projeto", "A": "", "C": "", "I": ""},
      {"atividade": "Desenvolver código", "R": "Desenvolvedor", "A": "Gerente Projeto", "C": "", "I": ""},
      {"atividade": "Revisar código", "R": "", "A": "Gerente Projeto", "C": "Revisor", "I": ""},
      {"atividade": "Testar funcionalidades", "R": "Desenvolvedor", "A": "Gerente Projeto", "C": "", "I": ""},
      {"atividade": "Deploy produção", "R": "Gerente Projeto", "A": "Patrocinador", "C": "", "I": ""},
      {"atividade": "Documentar projeto", "R": "Gerente Projeto", "A": "", "C": "", "I": ""}
    ]
  },
  "riscos": [
    {"id": 1, "descricao": "Escopo pode expandir além do necessário (scope creep)", "categoria": "Escopo", "probabilidade": "Alta", "impacto": "Médio", "estrategia": "Evitar", "plano_mitigacao": "Definir escopo claro e revisar antes de adicionar novas funcionalidades", "status": "ativo"},
    {"id": 2, "descricao": "Dados localStorage podem ser perdidos", "categoria": "Técnico", "probabilidade": "Média", "impacto": "Alto", "estrategia": "Mitigar", "plano_mitigacao": "Implementar sistema de backup/export", "status": "ativo"},
    {"id": 3, "descricao": "Dificuldade em exportar dados", "categoria": "Técnico", "probabilidade": "Média", "impacto": "Baixo", "estrategia": "Mitigar", "plano_mitigacao": "Adicionar funcionalidade de exportação JSON/CSV", "status": "em_tratamento"},
    {"id": 4, "descricao": "Performance pode degradas com muitos projetos", "categoria": "Técnico", "probabilidade": "Baixa", "impacto": "Médio", "estrategia": "Mitigar", "plano_mitigacao": "Otimizar renderização e implementar paginação", "status": "ativo"},
    {"id": 5, "descricao": "Compatibilidade com dispositivos móveis", "categoria": "Técnico", "probabilidade": "Baixa", "impacto": "Alto", "estrategia": "Mitigar", "plano_mitigacao": "Testar em múltiplos dispositivos e corrigir responsividade", "status": "em_tratamento"}
  ],
  "marcos": [
    {"id": "M1", "nome": "Projeto Iniciado", "data_alvo": "2024-03-08", "status": "concluido", "entregavel": "Repositório criado e estrutura definida"},
    {"id": "M2", "nome": "MVP Released", "data_alvo": "2024-04-01", "status": "concluido", "entregavel": "Versão básica com dashboard e mapa funcional"},
    {"id": "M3", "nome": "Template System", "data_alvo": "2024-05-01", "status": "concluido", "entregavel": "Sistema de templates implementado"},
    {"id": "M4", "nome": "Kanban Completo", "data_alvo": "2024-06-01", "status": "em_andamento", "entregavel": "Board kanban completo com drag-and-drop"},
    {"id": "M5", "nome": "Mobile Ready", "data_alvo": "2024-09-01", "status": "em_andamento", "entregavel": "Versão Android/iOS via Capacitor"},
    {"id": "M6", "nome": "Desktop App", "data_alvo": "2025-03-01", "status": "pendente", "entregavel": "Versão desktop via Tauri"},
    {"id": "M7", "nome": "Projeto Encerrado", "data_alvo": "2026-12-31", "status": "pendente", "entregavel": "Documentação final e lições aprendidas"}
  ],
  "metricas": {
    "horas_estimadas_total": 500,
    "horas_gastas": 156,
    "horas_restantes": 344,
    "percentual_concluido": 31.2,
    "prazo_estimado": "2026-12-31",
    "prazo_atual": "2026-04-03",
    "tempo_decorrido_meses": 24,
    "tempo_restante_meses": 21,
    "indice_desempenho_prazo_spi": 1.3,
    "indice_desempenho_custo_cpi": 1.0,
    "valor_planejado": 156,
    "valor_ganho": 200,
    "custo_real": 156,
    "projetos_total": 5,
    "projetos_concluidos": 2,
    "atividades_total": 45,
    "atividades_concluidas": 18,
    "atividades_andamento": 15,
    "atividades_pendentes": 12
  },
  "cronograma": {
    "tarefas": [
      {"id": "T1", "nome": "Definir requisitos", "duracao_dias": 3, "inicio": "2024-03-08", "fim": "2024-03-11", "dependencias": [], "responsavel": "Wander", "progresso": 100, "critico": true},
      {"id": "T2", "nome": "Criar documento de visão", "duracao_dias": 2, "inicio": "2024-03-12", "fim": "2024-03-13", "dependencias": ["T1"], "responsavel": "Wander", "progresso": 100, "critico": true},
      {"id": "T3", "nome": "Definir arquitetura técnica", "duracao_dias": 3, "inicio": "2024-03-14", "fim": "2024-03-16", "dependencias": ["T2"], "responsavel": "Wander", "progresso": 100, "critico": true},
      {"id": "T4", "nome": "Criar estrutura de diretórios", "duracao_dias": 1, "inicio": "2024-03-17", "fim": "2024-03-17", "dependencias": ["T3"], "responsavel": "Wander", "progresso": 100, "critico": false},
      {"id": "T5", "nome": "Definir templates de projetos", "duracao_dias": 4, "inicio": "2024-03-18", "fim": "2024-03-21", "dependencias": ["T3"], "responsavel": "Wander", "progresso": 100, "critico": false},
      {"id": "T6", "nome": "Planejar sistema de dados", "duracao_dias": 2, "inicio": "2024-03-22", "fim": "2024-03-23", "dependencias": ["T3"], "responsavel": "Wander", "progresso": 50, "critico": false},
      {"id": "T7", "nome": "Criar estrutura HTML base", "duracao_dias": 7, "inicio": "2024-03-24", "fim": "2024-03-30", "dependencias": ["T4"], "responsavel": "Wander", "progresso": 100, "critico": true},
      {"id": "T8", "nome": "Implementar CSS global", "duracao_dias": 5, "inicio": "2024-03-25", "fim": "2024-03-29", "dependencias": ["T4"], "responsavel": "Wander", "progresso": 100, "critico": false},
      {"id": "T9", "nome": "Desenvolver componente Header", "duracao_dias": 2, "inicio": "2024-03-30", "fim": "2024-03-31", "dependencias": ["T7"], "responsavel": "Wander", "progresso": 100, "critico": false},
      {"id": "T10", "nome": "Desenvolver componente Footer", "duracao_dias": 1, "inicio": "2024-03-31", "fim": "2024-03-31", "dependencias": ["T9"], "responsavel": "Wander", "progresso": 100, "critico": false},
      {"id": "T11", "nome": "Implementar dashboard de projetos", "duracao_dias": 7, "inicio": "2024-04-01", "fim": "2024-04-07", "dependencias": ["T7"], "responsavel": "Wander", "progresso": 70, "critico": true},
      {"id": "T12", "nome": "Criar sistema de modais", "duracao_dias": 4, "inicio": "2024-04-02", "fim": "2024-04-05", "dependencias": ["T7"], "responsavel": "Wander", "progresso": 60, "critico": false},
      {"id": "T13", "nome": "Implementar engine do mapa", "duracao_dias": 10, "inicio": "2024-04-08", "fim": "2024-04-17", "dependencias": ["T11"], "responsavel": "Wander", "progresso": 65, "critico": true},
      {"id": "T14", "nome": "Adicionar sistema de drag-and-drop", "duracao_dias": 4, "inicio": "2024-04-18", "fim": "2024-04-21", "dependencias": ["T13"], "responsavel": "Wander", "progresso": 0, "critico": false},
      {"id": "T15", "nome": "Criar painel de dependências", "duracao_dias": 4, "inicio": "2024-04-22", "fim": "2024-04-25", "dependencias": ["T13"], "responsavel": "Wander", "progresso": 0, "critico": false},
      {"id": "T16", "nome": "Implementar board kanban", "duracao_dias": 8, "inicio": "2024-04-08", "fim": "2024-04-15", "dependencias": ["T12"], "responsavel": "Wander", "progresso": 75, "critico": false},
      {"id": "T17", "nome": "Adicionar drag entre colunas", "duracao_dias": 4, "inicio": "2024-04-16", "fim": "2024-04-19", "dependencias": ["T16"], "responsavel": "Wander", "progresso": 0, "critico": false},
      {"id": "T18", "nome": "Configurar Capacitor", "duracao_dias": 2, "inicio": "2024-04-26", "fim": "2024-04-27", "dependencias": ["T15"], "responsavel": "Wander", "progresso": 100, "critico": false},
      {"id": "T19", "nome": "Configurar Tauri", "duracao_dias": 2, "inicio": "2024-04-28", "fim": "2024-04-29", "dependencias": ["T18"], "responsavel": "Wander", "progresso": 100, "critico": false},
      {"id": "T20", "nome": "Compilar versão Android", "duracao_dias": 4, "inicio": "2024-04-30", "fim": "2024-05-03", "dependencias": ["T18"], "responsavel": "Wander", "progresso": 0, "critico": false}
    ],
    "caminho_critico": ["T1", "T2", "T3", "T7", "T11", "T13"],
    "duracao_total_dias": 87,
    "data_inicio_projeto": "2024-03-08",
    "data_fim_projeto": "2024-06-03"
  }
}